rudra/__init__.py
rudra/agent.py
rudra-0.0.2.dist-info/LICENSE
rudra-0.0.2.dist-info/METADATA
rudra-0.0.2.dist-info/WHEEL
rudra-0.0.2.dist-info/RECORD
