Metadata-Version: 2.1
Name: rudra
Version: 0.0.2
Summary: A flexible OpenAI-standard agent with customizable tool integration
License: MIT
Author: Subhrajit Mohanty
Author-email: subhrajitm07@gmail.com
Requires-Python: >=3.9,<4.0
Classifier: License :: OSI Approved :: MIT License
Classifier: Programming Language :: Python :: 3
Classifier: Programming Language :: Python :: 3.9
Classifier: Programming Language :: Python :: 3.10
Classifier: Programming Language :: Python :: 3.11
Classifier: Programming Language :: Python :: 3.12
